spci/__init__.py
spci/calc_atomic_properties_chemaxon.py
spci/calc_frag_contrib.py
spci/default.smarts
spci/descriptors.py
spci/extractsdf.py
spci/filter_descriptors.py
spci/find_frags_auto_rdkit.py
spci/find_frags_rdkit.py
spci/find_murcko_rdkit.py
spci/model.py
spci/mol_context.py
spci/plot_contributions.py
spci/plot_property_distribution.py
spci/predict.py
spci/sdf_field2title.py
spci/setup.txt
spci/sirms_file_class.py
spci/spci.py
spci/std_rules.xml
spci-1.1.5.dist-info/METADATA
spci-1.1.5.dist-info/WHEEL
spci-1.1.5.dist-info/entry_points.txt
spci-1.1.5.dist-info/top_level.txt
spci-1.1.5.dist-info/RECORD
