Metadata-Version: 2.1
Name: spci
Version: 1.1.5
Summary: SPCI: structural and physicochemical interpretation of QSAR models
Home-page: https://github.com/DrrDom/spci
Author: Pavel Polishchuk
Author-email: pavel_polishchuk@ukr.net
Classifier: Programming Language :: Python :: 3
Classifier: License :: OSI Approved :: GNU Lesser General Public License v3 (LGPLv3)
Classifier: Operating System :: OS Independent
Classifier: Topic :: Scientific/Engineering :: Bio-Informatics
Classifier: Topic :: Scientific/Engineering :: Chemistry
Requires-Python: >=3.6
Requires-Dist: sirms >=1.2.0
Provides-Extra: rdkit
Requires-Dist: rdkit >=2017.09 ; extra == 'rdkit'
